adbc_driver_manager/__init__.py
adbc_driver_manager/_backward.cpython-312-x86_64-linux-gnu.so
adbc_driver_manager/_backward.pyx
adbc_driver_manager/_blocking_impl.cc
adbc_driver_manager/_blocking_impl.h
adbc_driver_manager/_dbapi_backend.py
adbc_driver_manager/_lib.cpython-312-x86_64-linux-gnu.so
adbc_driver_manager/_lib.pxd
adbc_driver_manager/_lib.pyi
adbc_driver_manager/_lib.pyx
adbc_driver_manager/_reader.cpython-312-x86_64-linux-gnu.so
adbc_driver_manager/_reader.pyi
adbc_driver_manager/_reader.pyx
adbc_driver_manager/_static_version.py
adbc_driver_manager/_version.py
adbc_driver_manager/adbc_driver_manager.cc
adbc_driver_manager/backward.hpp
adbc_driver_manager/current_arch.h
adbc_driver_manager/dbapi.py
adbc_driver_manager/py.typed
adbc_driver_manager/arrow-adbc/adbc.h
adbc_driver_manager/arrow-adbc/adbc_driver_manager.h
adbc_driver_manager/toml++/toml.hpp
adbc_driver_manager-1.10.0.dist-info/METADATA
adbc_driver_manager-1.10.0.dist-info/WHEEL
adbc_driver_manager-1.10.0.dist-info/top_level.txt
adbc_driver_manager-1.10.0.dist-info/RECORD
adbc_driver_manager-1.10.0.dist-info/licenses/LICENSE.txt
adbc_driver_manager-1.10.0.dist-info/licenses/NOTICE.txt
